Workbook

Sheet KALSHI_TRADES
A1: trade_date | B1: contract_id | C1: market | D1: direction | E1: entry_price | F1: exit_price | G1: num_contracts | H1: cost_basis | I1: pnl_realized | J1: pnl_unrealized | K1: status | L1: expiry_date | M1: fees | N1: notes
A2: 46054 | B2: TEMP.HIGH.SEA-2026-02-01 | C2: Weather | D2: YES | E2: 0.42 | F2: 1 | G2: 500 | H2: =E2*G2 | I2: =IF(K2="Settled",(F2-E2)*G2-M2,"") | J2: =IF(K2="Open",(F2-E2)*G2,"") | K2: Settled | L2: 46054 | M2: 8.4 | N2: GFS match
A3: 46055 | B3: RAIN.PDX.0.25IN-2026-02-02 | C3: Weather | D3: YES | E3: 0.61 | F3: 0 | G3: 300 | H3: =E3*G3 | I3: =IF(K3="Settled",(F3-E3)*G3-M3,"") | J3: =IF(K3="Open",(F3-E3)*G3,"") | K3: Settled | L3: 46055 | M3: 5.49 | N3: Miss
A4: 46058 | B4: FED.HOLD.MAR26 | C4: Macro | D4: YES | E4: 0.72 | G4: 1000 | H4: =E4*G4 | I4: =IF(K4="Settled",(F4-E4)*G4-M4,"") | J4: =IF(K4="Open",(F4-E4)*G4,"") | K4: Open | L4: 46100 | M4: 0
A5: 46063 | B5: BTC.ABOVE.80K-2026-02-10 | C5: Crypto | D5: YES | E5: 0.68 | F5: 1 | G5: 500 | H5: =E5*G5 | I5: =IF(K5="Settled",(F5-E5)*G5-M5,"") | J5: =IF(K5="Open",(F5-E5)*G5,"") | K5: Settled | L5: 46063 | M5: 10.2
A6: 46067 | B6: SNOW.CHI.1IN-2026-02-14 | C6: Weather | D6: YES | E6: 0.55 | F6: 0 | G6: 300 | H6: =E6*G6 | I6: =IF(K6="Settled",(F6-E6)*G6-M6,"") | J6: =IF(K6="Open",(F6-E6)*G6,"") | K6: Settled | L6: 46067 | M6: 5.5
A7: 46071 | B7: CPI.ABOVE.3-2026-03 | C7: Macro | D7: YES | E7: 0.32 | G7: 250 | H7: =E7*G7 | I7: =IF(K7="Settled",(F7-E7)*G7-M7,"") | J7: =IF(K7="Open",(F7-E7)*G7,"") | K7: Open | L7: 46093 | M7: 0
A8: 46073 | B8: TEMP.HIGH.NYC-2026-02-26 | C8: Weather | D8: YES | E8: 0.42 | F8: 1 | G8: 245 | H8: =E8*G8 | I8: =IF(K8="Settled",(F8-E8)*G8-M8,"") | J8: =IF(K8="Open",(F8-E8)*G8,"") | K8: Settled | L8: 46079 | M8: 4.66
A9: 46075 | B9: RAIN.SEA.1IN-2026-02-28 | C9: Weather | D9: YES | E9: 0.38 | G9: 1000 | H9: =E9*G9 | I9: =IF(K9="Settled",(F9-E9)*G9-M9,"") | J9: =IF(K9="Open",(F9-E9)*G9,"") | K9: Open | L9: 46081 | M9: 0
A11: ⚠ REPLACE SAMPLE DATA: Run kalshi_sync.py to populate with real Scalper trades

Sheet JOHN_REVENUE
A1: date | B1: client_name | C1: service_type | D1: amount | E1: recurring | F1: invoice_status | G1: payment_method | H1: notes
A2: 46054 | B2: Bothell Landscaping Co. | C2: Website + Email | D2: 349 | E2: Y | F2: Paid | G2: Stripe | H2: New client Feb
A3: 46054 | B3: Pacific NW Plumbers | C3: Website + SEO | D3: 199 | E3: Y | F3: Paid | G3: Stripe | H3: Monthly recurring
A4: 46054 | B4: Kirkland Dental | C4: Hosting | D4: 149 | E4: Y | F4: Paid | G4: Stripe | H4: Monthly recurring
A5: 46054 | B5: Redmond Auto Detail | C5: Email Campaigns | D5: 99 | E5: Y | F5: Pending | G5: ACH | H5: Invoice sent 2/1
A6: 46058 | B6: Shoreline Gym | C6: Website Build | D6: 1200 | E6: N | F6: Paid | G6: Stripe | H6: One-time build
A7: 46063 | B7: Kenmore HVAC | C7: Website + Email | D7: 179 | E7: Y | F7: Paid | G7: Stripe | H7: Monthly recurring
A8: 46067 | B8: Lynnwood Café | C8: Website Build | D8: 950 | E8: N | F8: Paid | G8: Cash | H8: One-time build
A9: 46071 | B9: Mountlake Florist | C9: Email Only | D9: 89 | E9: Y | F9: Paid | G9: Stripe | H9: Monthly recurring
A10: 46075 | B10: Bothell Tax Svc | C10: Website + SEO | D10: 225 | E10: Y | F10: Paid | G10: Stripe | H10: Monthly recurring
A11: 46078 | B11: Edmonds Realty | C11: Website Build | D11: 1500 | E11: N | F11: Pending | G11: ACH | H11: Invoice outstanding
A12: 46079 | B12: Mukilteo Bakery | C12: Hosting | D12: 79 | E12: Y | F12: Paid | G12: Stripe | H12: Monthly recurring
A13: 46080 | B13: Kenmore Dentist | C13: Website Build | D13: 1200 | E13: N | F13: Paid | G13: Stripe | H13: One-time build
A15: SUMMARY FORMULAS
A16: Total Revenue (MTD) | B16: =SUMPRODUCT((MONTH(A2:A13)=MONTH(TODAY()))*(D2:D13))
A17: MRR | B17: =SUMPRODUCT((E2:E13="Y")*(D2:D13))
A18: Pending Invoices | B18: =SUMPRODUCT((F2:F13="Pending")*(D2:D13))
A19: Active Clients | B19: =COUNTA(B2:B13)

Sheet KELSEA_TRANSACTIONS
A1: date | B1: transaction_type | C1: category | D1: description | E1: amount | F1: payment_status | G1: reference
A2: 46054 | B2: Revenue | C2: Sales | D2: Product sales - Feb wk1 | E2: 1240 | F2: Cleared | G2: INV-001
A3: 46056 | B3: Expense | C3: COGS | D3: Supplier payment - goods | E3: 480 | F3: Cleared | G3: PO-441
A4: 46058 | B4: Revenue | C4: Services | D4: Consulting fee | E4: 800 | F4: Cleared | G4: INV-002
A5: 46061 | B5: Expense | C5: Software | D5: Subscriptions - tools | E5: 120 | F5: Cleared | G5: AUTO
A6: 46063 | B6: Revenue | C6: Sales | D6: Product sales - Feb wk2 | E6: 980 | F6: Cleared | G6: INV-003
A7: 46065 | B7: Expense | C7: COGS | D7: Supplier payment - goods | E7: 360 | F7: Cleared | G7: PO-442
A8: 46068 | B8: Revenue | C8: Sales | D8: Product sales - Feb wk3 | E8: 1100 | F8: Cleared | G8: INV-004
A9: 46071 | B9: Expense | C9: Marketing | D9: Ad spend | E9: 180 | F9: Cleared | G9: FB-ADS
A10: 46073 | B10: Revenue | C10: Services | D10: Consulting fee | E10: 620 | F10: Pending | G10: INV-005
A11: 46075 | B11: Expense | C11: COGS | D11: Supplier payment | E11: 284 | F11: Cleared | G11: PO-443
A12: 46078 | B12: Revenue | C12: Sales | D12: Product sales - Feb wk4 | E12: 920 | F12: Cleared | G12: INV-006
A13: 46080 | B13: Expense | C13: Overhead | D13: Misc overhead | E13: 180 | F13: Cleared | G13: MISC

Sheet AI_TOKEN_USAGE
A1: date | B1: agent_name | C1: model | D1: input_tokens | E1: output_tokens | F1: total_tokens | G1: cost_usd | H1: purpose
A2: 46054 | B2: Cliff | C2: claude-sonnet-4-6 | D2: 106729 | E2: 35269 | F2: =D2+E2 | G2: 0.849222 | H2: Analysis
A3: 46054 | B3: Scalper V8 | C3: claude-haiku-4-5-20251001 | D3: 36370 | E3: 23216 | F3: =D3+E3 | G3: 0.0381125 | H3: Trading
A4: 46054 | B4: NorthStar Sales | C4: claude-haiku-4-5-20251001 | D4: 128050 | E4: 35864 | F4: =D4+E4 | G4: 0.0768425 | H4: Sales
A5: 46054 | B5: WBR Agent | C5: claude-sonnet-4-6 | D5: 88239 | E5: 27121 | F5: =D5+E5 | G5: 0.671532 | H5: Reporting
A6: 46055 | B6: Cliff | C6: claude-sonnet-4-6 | D6: 63325 | E6: 26629 | F6: =D6+E6 | G6: 0.58941 | H6: Analysis
A7: 46055 | B7: Scalper V8 | C7: claude-haiku-4-5-20251001 | D7: 192989 | E7: 17213 | F7: =D7+E7 | G7: 0.0697635 | H7: Trading
A8: 46055 | B8: NorthStar Sales | C8: claude-haiku-4-5-20251001 | D8: 157984 | E8: 10590 | F8: =D8+E8 | G8: 0.0527335 | H8: Sales
A9: 46055 | B9: WBR Agent | C9: claude-sonnet-4-6 | D9: 185470 | E9: 21836 | F9: =D9+E9 | G9: 0.88395 | H9: Reporting
A10: 46056 | B10: Cliff | C10: claude-sonnet-4-6 | D10: 20028 | E10: 15398 | F10: =D10+E10 | G10: 0.291054 | H10: Analysis
A11: 46056 | B11: Scalper V8 | C11: claude-haiku-4-5-20251001 | D11: 178570 | E11: 7979 | F11: =D11+E11 | G11: 0.05461625 | H11: Trading
A12: 46056 | B12: NorthStar Sales | C12: claude-haiku-4-5-20251001 | D12: 108221 | E12: 13769 | F12: =D12+E12 | G12: 0.0442665 | H12: Sales
A13: 46056 | B13: WBR Agent | C13: claude-sonnet-4-6 | D13: 160465 | E13: 22112 | F13: =D13+E13 | G13: 0.813075 | H13: Reporting
... A109: 46080 | B109: WBR Agent | C109: claude-sonnet-4-6 | D109: 60077 | E109: 16129 | F109: =D109+E109 | G109: 0.422166 | H109: Reporting

Sheet EXPENSES_ALL
A1: date | B1: business_line | C1: category | D1: vendor | E1: amount | F1: recurring | G1: notes
A2: 46054 | B2: Shared | C2: API | D2: Anthropic (Cliff) | E2: 224 | F2: Y | G2: claude-sonnet-4-6 MTD
A3: 46054 | B3: Betting | C3: API | D3: Anthropic (Scalper) | E3: 57 | F3: Y | G3: claude-haiku-4-5 MTD
A4: 46054 | B4: Shared | C4: API | D4: Anthropic (Sales Agent) | E4: 18 | F4: Y | G4: MTD
A5: 46054 | B5: Shared | C5: Hosting | D5: Railway | E5: 20 | F5: Y | G5: Production hosting
A6: 46054 | B6: John | C6: Hosting | D6: Hostinger | E6: 15 | F6: Y | G6: Client hosting
A7: 46054 | B7: Shared | C7: Software | D7: Cursor Pro | E7: 20 | F7: Y | G7: IDE subscription
A8: 46054 | B8: Betting | C8: Software | D8: Kalshi fees | E8: 48 | F8: N | G8: Trading fees MTD
A9: 46056 | B9: Kelsea | C9: COGS | D9: Supplier A | E9: 480 | F9: N | G9: Goods purchase
A10: 46058 | B10: John | C10: Marketing | D10: Google Ads | E10: 200 | F10: Y | G10: Lead gen
A11: 46061 | B11: Kelsea | C11: Software | D11: Tools bundle | E11: 120 | F11: Y | G11: Monthly subs
A12: 46071 | B12: Kelsea | C12: Marketing | D12: Facebook Ads | E12: 180 | F12: N | G12: Ad spend
A13: 46075 | B13: Kelsea | C13: COGS | D13: Supplier A | E13: 284 | F13: N | G13: Goods purchase
... A15: 46080 | B15: Kelsea | C15: Overhead | D15: Misc | E15: 180 | F15: N | G15: Miscellaneous

Sheet DAILY_SUMMARY
A1: NorthStar Synergy — P&L Master Summary
A2: Last refreshed: | B2: =NOW()
A4: ━━ BETTING / KALSHI (MTD) ━━
A5: Gross Wins | B5: =SUMPRODUCT((MONTH(KALSHI_TRADES!A2:A1000)=MONTH(TODAY()))*(KALSHI_TRADES!K2:K1000="Settled")*(KALSHI_TRADES!I2:I1000>0)*(KALSHI_TRADES!I2:I1000))
A6: Gross Losses | B6: =SUMPRODUCT((MONTH(KALSHI_TRADES!A2:A1000)=MONTH(TODAY()))*(KALSHI_TRADES!K2:K1000="Settled")*(KALSHI_TRADES!I2:I1000<0)*(KALSHI_TRADES!I2:I1000))
A7: Net P&L (Betting) | B7: =SUMPRODUCT((MONTH(KALSHI_TRADES!A2:A1000)=MONTH(TODAY()))*(KALSHI_TRADES!K2:K1000="Settled")*(KALSHI_TRADES!I2:I1000))
A8: Open Positions Count | B8: =COUNTIF(KALSHI_TRADES!K2:K1000,"Open")
A9: Current Exposure (Open) | B9: =SUMPRODUCT((KALSHI_TRADES!K2:K1000="Open")*(KALSHI_TRADES!H2:H1000))
A10: Unrealized P&L | B10: =SUMPRODUCT((KALSHI_TRADES!K2:K1000="Open")*(IFERROR(KALSHI_TRADES!J2:J1000,0)))
A11: Win Rate | B11: =IFERROR(SUMPRODUCT((MONTH(KALSHI_TRADES!A2:A1000)=MONTH(TODAY()))*(KALSHI_TRADES!K2:K1000="Settled")*(KALSHI_TRADES!I2:I1000>0))/SUMPRODUCT((MONTH(KALSHI_TRADES!A2:A1000)=MONTH(TODAY()))*(KALSHI_TRADES!K2:K1000="Settled")*1),0)
A13: ━━ JOHN'S WEB BIZ (MTD) ━━
A14: Total Revenue | B14: =SUMPRODUCT((MONTH(JOHN_REVENUE!A2:A1000)=MONTH(TODAY()))*(JOHN_REVENUE!D2:D1000))
A15: MRR (Recurring Only) | B15: =SUMPRODUCT((JOHN_REVENUE!E2:E1000="Y")*(JOHN_REVENUE!D2:D1000))
A16: Pending Invoices | B16: =SUMPRODUCT((JOHN_REVENUE!F2:F1000="Pending")*(JOHN_REVENUE!D2:D1000))
A18: ━━ KELSEA BUSINESSES (MTD) ━━
A19: Total Revenue | B19: =SUMPRODUCT((MONTH(KELSEA_TRANSACTIONS!A2:A1000)=MONTH(TODAY()))*(KELSEA_TRANSACTIONS!B2:B1000="Revenue")*(KELSEA_TRANSACTIONS!E2:E1000))
A20: Total Expenses | B20: =SUMPRODUCT((MONTH(KELSEA_TRANSACTIONS!A2:A1000)=MONTH(TODAY()))*(KELSEA_TRANSACTIONS!B2:B1000="Expense")*(KELSEA_TRANSACTIONS!E2:E1000))
A21: Net Profit | B21: =SUMPRODUCT((MONTH(KELSEA_TRANSACTIONS!A2:A1000)=MONTH(TODAY()))*(KELSEA_TRANSACTIONS!B2:B1000="Revenue")*(KELSEA_TRANSACTIONS!E2:E1000))-SUMPRODUCT((MONTH(KELSEA_TRANSACTIONS!A2:A1000)=MONTH(TODAY()))*(KELSEA_TRANSACTIONS!B2:B1000="Expense")*(KELSEA_TRANSACTIONS!E2:E1000))
A23: ━━ AI / TOKEN COSTS (MTD) ━━
A24: Total Token Cost | B24: =SUMPRODUCT((MONTH(AI_TOKEN_USAGE!A2:A5000)=MONTH(TODAY()))*(AI_TOKEN_USAGE!G2:G5000))
A25: Cliff Token Cost | B25: =SUMPRODUCT((MONTH(AI_TOKEN_USAGE!A2:A5000)=MONTH(TODAY()))*(AI_TOKEN_USAGE!B2:B5000="Cliff")*(AI_TOKEN_USAGE!G2:G5000))
A26: Scalper Token Cost | B26: =SUMPRODUCT((MONTH(AI_TOKEN_USAGE!A2:A5000)=MONTH(TODAY()))*(AI_TOKEN_USAGE!B2:B5000="Scalper V8")*(AI_TOKEN_USAGE!G2:G5000))
A28: ━━ ENTERPRISE TOTALS (MTD) ━━
A29: ALL REVENUE | B29: =SUMPRODUCT((MONTH(JOHN_REVENUE!A2:A1000)=MONTH(TODAY()))*(JOHN_REVENUE!D2:D1000))+SUMPRODUCT((MONTH(KELSEA_TRANSACTIONS!A2:A1000)=MONTH(TODAY()))*(KELSEA_TRANSACTIONS!B2:B1000="Revenue")*(KELSEA_TRANSACTIONS!E2:E1000))
A30: ALL EXPENSES | B30: =SUMPRODUCT((MONTH(EXPENSES_ALL!A2:A1000)=MONTH(TODAY()))*(EXPENSES_ALL!E2:E1000))
A31: ALL NET P&L | B31: =B28+B17-B29
